<tables xmlns="http://labkey.org/data/xml">
  <table tableName="service_accounts" tableDbType="TABLE">
    <columns>
      <column columnName="id"/>
      <column columnName="display_name"/>
      <column columnName="project_id"/>
      <column columnName="private_key_id"/>
      <column columnName="private_key"/>
      <column columnName="client_email"/>
      <column columnName="client_id"/>
      <column columnName="auth_uri"/>
      <column columnName="token_uri"/>
      <column columnName="client_x509_cert_url"/>
      <column columnName="auth_provider_x509_cert_url"/>
      <column columnName="createdby"/>
      <column columnName="created"/>
      <column columnName="modifiedby"/>
      <column columnName="modified"/>
    </columns>
  </table>
</tables>