<query xmlns="http://labkey.org/data/xml/query">
    <metadata>
        <tables xmlns="http://labkey.org/data/xml">
            <table tableName="Surgeries" tableDbType="TABLE">
                <tableUrl>/EHR/surgeryDetails.view?key=${objectid}</tableUrl>
                <insertUrl />
                <importUrl />
                <updateUrl />
                <deleteUrl />
                <columns>
                    <column columnName="project">
                        <fk>
                            <fkDbSchema>ehr</fkDbSchema>
                            <fkTable>project</fkTable>
                            <fkColumnName>project</fkColumnName>
                        </fk>
                    </column>
                    <column columnName="enddate">
                        <columnTitle>End Date</columnTitle>
                    </column>
                    <column columnName="parentid">
                        <!--<fk>-->
                          <!--<fkDbSchema>study</fkDbSchema>-->
                          <!--<fkTable>studyDataParent</fkTable>-->
                          <!--<fkColumnName>objectid</fkColumnName>-->
                        <!--</fk>-->
                    </column>
                </columns>
            </table>
        </tables>
    </metadata>
</query>